relaxtemplates/__init__.py
relaxtemplates/base.py
relaxtemplates-1.0.2.dist-info/LICENSE
relaxtemplates-1.0.2.dist-info/METADATA
relaxtemplates-1.0.2.dist-info/WHEEL
relaxtemplates-1.0.2.dist-info/top_level.txt
relaxtemplates-1.0.2.dist-info/RECORD
