Metadata-Version: 2.1
Name: relaxtemplates
Version: 1.0.2
Summary: A Python-based template engine that features variables, conditionals, loops, call, extends, includes, comments, and more, making it easy to create dynamic web pages.
Home-page: https://github.com/Ravikisha/relaxtemplates
Author: Ravi Kishan
Author-email: ravikishan63392@gmail.com
License: MIT
Keywords: template engine,python,dynamic templates,web development,variables,conditionals,loops,includes,extends,comments
Classifier: Programming Language :: Python :: 3
Classifier: Programming Language :: Python :: 3.8
Classifier: Programming Language :: Python :: 3.9
Classifier: Programming Language :: Python :: 3.10
Classifier: Programming Language :: Python :: 3.11
Classifier: License :: OSI Approved :: MIT License
Classifier: Operating System :: OS Independent
Requires-Python: >=3.8
License-File: LICENSE
